{
  "title": "原告张翠英与被告胡旭明追索劳动报酬纠纷一案民事判决书",
  "content": {
    "litigants": [
      "原告:张翠英，女，1963年10月13日出生，汉族，山**省万荣县。",
      "委托诉讼代理人:贾卫强，男，山西荣强律师事务所律师。",
      "被告:胡旭明，男，1971年1月30日出生，汉族，浙江省，现租住山**省运城市万荣县。"
    ],
    "explain": [
      "原告张翠英与被告胡旭明追索劳动报酬纠纷一案，本院于2019年8月1日立案后，依法适用小额诉讼程序公开开庭进行了审理。"
    ],
    "procedure": [
      "原告诉讼委托代理人贾卫强到庭参加诉讼，被告胡旭明经本院传票传唤无正当理由拒不到庭参加诉讼，本案现已审理终结。",
      "原告张翠英向本院提出诉讼请求:1、判令被告支付原告工资4500元；2、判令被告承担本案诉讼费用。",
      "事实和理由:2018年8月6日被告与万荣县庄园服务中心签订租赁合同，租用庄园经营餐饮。",
      "原告被雇佣在被告处工作担任洗碗工，双方约定原告的月工资为1800元。",
      "至2018年12月15日被告拖欠原告工资4500元，并向原告出具了欠条。",
      "至今被告未支付拖欠原告的工资，请求依法支持原告的诉讼请求。",
      "原告围绕其诉讼请求依法向本院提交了以下证据:1、被告的身份证复印件，证明被告的基本信息；2、租赁合同，证明被告2018年8月10日租用万荣县庄园从事餐饮经营；3、欠条一份，证明被告拖欠原告工资4500元。",
      "被告胡旭明未作书面答辩。"
    ],
    "facts": [
      "本院经审理查明，2018年8月6日被告与万荣县庄园服务中心签订庄园租赁合同从事餐饮经营，2018年8月10日被告雇佣原告担任洗碗工工作，至2018年12月15日被告共拖欠原告工资4500元，并为原告出具欠条，约定在2019年1月10日还清。",
      "被告拖欠原告工资4500元至今未付。"
    ],
    "opinion": [
      "本院认为，2018年8月10日被告雇佣原告从事洗碗工工作，至2018年12月15日被告共拖欠原告工资4500元，并为原告出具欠条，原被告之间形成劳务合同法律关系，被告应当支付拖欠原告的工资。",
      "被告未按约定时间支付原告工资构成违约，应承担继续履行违约责任。",
      "原告的诉讼请求本院予以支持。"
    ],
    "verdict": [
      "依照《中华人民共和国合同法》第六十条  、第一百零七条  、第一百零九条  之规定，判决如下:",
      "被告胡旭明在本判决生效后十日内支付原告张翠英工资4500元。",
      "如果未按本判决指定的期间履行给付金钱义务，应当依照《中华人民共和国民事诉讼法》第二百五十三条  规定，加倍支付延迟履行期间的债务利息。",
      "案件受理费25元，由被告胡旭明负担。"
    ],
    "inform": [
      "本判决为终审判决。"
    ],
    "ending": [
      "审判员李作义",
      "二〇一九年八月二十六日",
      "书记员王媛媛"
    ]
  },
  "metadata": {
    "日期": "2019-08-26",
    "法院": "山西省万荣县人民法院",
    "案号": "（2019）晋0822民初1851号",
    "时间": "2019年08月26日",
    "案由": "追索劳动报酬纠纷",
    "类型": "判决书",
    "程序": "一审"
  }
}