{
  "title": "郑开双、曹茂春追索劳动报酬纠纷一审民事判决书",
  "content": {
    "litigants": [
      "原告:郑开双，男，汉族，1955年10月5日出生，住四川省阆中市。",
      "委托诉讼代理人:蔡生波，四川源正律师事务所律师。",
      "被告:曹茂春，男，汉族，1972年10月25日出生，住四川省南部县。"
    ],
    "explain": [
      "原告郑开双与被告曹茂春劳务合同纠纷一案，本院于2019年7月30日立案受理后，依法适用简易程序公开开庭进行了审理。"
    ],
    "procedure": [
      "原告郑开双及其委托诉讼代理人蔡生波到庭参加了诉讼，被告曹茂春经本院传票传唤，无正当理由拒不到庭。",
      "本案现已审理终结。",
      "原告郑开双向本院提出诉讼请求:1、判令被告立即支付原告的劳务费5000元，并从原告主张之日起按照年利率6%支付利息至清偿之日止。",
      "2、本案诉讼费由被告负担。",
      "事实和理由:被告承包阆中市七里南池四期廉租房小区建设劳务，原告从2016年4月份开始受被告雇佣从事建筑劳务。",
      "2017年1月25日，被告向原告出具欠条一张，载明欠原告人工工资10000元。",
      "后经原告催收，被告仅向原告支付了5000元，尚欠5000元未付。",
      "原告遂起诉至法院。",
      "被告曹茂春未到庭，也未提交书面答辩意见及相关证据。",
      "根据原告陈述及经审查确认的证据，本院认定事实如下:被告承包阆中市七里南池四期廉租房小区建设劳务，原告郑开双从2016年4月份开始受被告曹茂春雇佣从事建筑劳务。",
      "2017年1月25日，原、被告进行了结算。",
      "被告曹茂春欠原告人工工资10000元，并向原告出具欠条一张。",
      "欠条出具后，经原告多次催收，被告曹茂春在2017年6月支付原告郑开双5000元，尚欠原告5000元。",
      "原告向被告收款无着。",
      "上述事实，有欠条及庭审笔录为据，足以认定。"
    ],
    "opinion": [
      "本院认为，公民的合法收入受法律保护。",
      "原告郑开双受雇于被告曹茂春作劳务，双方的劳务关系明确，被告曹茂春作为雇主，应当依照约定及时向原告郑开双支付劳动报酬，拖欠不付的行为损害了原告的合法权益，应当承担相应的民事责任。",
      "原告郑开双主张被告曹茂春支付其劳务费及资金占用利息的诉诉请求，符合法律规定，本院予以支持。"
    ],
    "verdict": [
      "综上，依照《中华人民共和国民法总则》第一百一十三条、第一百一十八条、第一百七十六条和《中华人民共和国民事诉讼法》第一百四十四条  的规定，判决如下:",
      "被告曹茂春在本判决发生法律效力后十五日内支付原告郑开双劳务费5000元及利息（以5000元为基数，从2019年7月30日起按照年利率6%计算至清偿之日止）。",
      "如果未按本判决指定的期间履行给付金钱义务，应当依照《中华人民共和国民事诉讼法》第二百五十三条  的规定，加倍支付迟延履行期间的债务利息。",
      "案件受理费25元，由被告曹茂春负担。"
    ],
    "inform": [
      "如不服本判决，可在判决书送达之日起十五日内，向本院递交上诉状，并按对方当事人的人数提出副本，上诉于四川省南充市中级人民法院。"
    ],
    "ending": [
      "审判员陈利",
      "二〇一九年八月十四日",
      "书记员牛杰"
    ]
  },
  "metadata": {
    "日期": "2019-08-26",
    "法院": "阆中市人民法院",
    "案号": "（2019）川1381民初4211号",
    "时间": "2019年08月26日",
    "案由": "追索劳动报酬纠纷",
    "类型": "判决书",
    "程序": "一审"
  }
}