{
  "title": "李小霞、李彦芹等与甄田玺等追索劳动报酬纠纷一审民事判决书",
  "content": {
    "litigants": [
      "原告:李小霞，女，1968年3月21日出生，汉族，住博野县。",
      "原告:李彦芹，女，1968年8月1日出生，汉族，住博野县。",
      "原告:赵小敏，女，1967年4月20日出生，汉族，住博野县。",
      "原告:费彩玲，女，1956年8月5日出生，汉族，住博野县。",
      "原告:史小彩，女，1949年8月25日出生，汉族，住博野县。",
      "原告:张爱平，女，1954年6月20日出生，汉族，住博野县。",
      "原告:李小舵，男，1968年2月20日出生，汉族，住博野县。",
      "原告:张荣芳，女，1959年5月1日出生，汉族，住博野县。",
      "原告:李胜吉，女，1957年8月25日出生，汉族，住博野县。",
      "原告:楚书芳，女，1956年8月15日出生，汉族，住博野县。",
      "原告:李二忠，男，1971年2月2日出生，汉族，住博野县。",
      "原告:李金风，女，1959年8月9日出生，汉族，住博野县。",
      "原告:李盼杰，男，1961年10月25日出生，汉族，住博野县。",
      "原告:白瑞苓，女，1959年8月1日出生，汉族，住博野县。",
      "原告:李小分，女，1959年8月18日出生，汉族，住博野县。",
      "原告:李跃春，男，1972年1月2日出生，汉族，住博野县。",
      "原告:刘景峰，男，1942年12月12日出生，汉族，住博野县。",
      "原告:林红珍，女，1968年5月4日出生，汉族，住博野县。",
      "原告:李小辈，男，1969年6月19日出生，汉族，住博野县。",
      "原告:李瑞，女，1952年6月7日出生，汉族，住博野县。",
      "以上二十名",
      "原告共同",
      "诉讼代表人:李盼杰，男，1961年10月25日出生，汉族，住博野县。",
      "刘景峰，男，1942年12月12日出生，汉族，住博野县。",
      "被告:甄田玺，男，成年，汉族，住博野县。",
      "被告:博野县丰农家庭农场。",
      "住所地，博野县南小王乡李家陀村中路南。",
      "经营者:甄田玺,厂长。"
    ],
    "explain": [
      "原告李小霞、李彦芹、赵小敏、费彩玲、史小彩、张爱平、李小舵、张荣芳、李胜吉、楚书芳、李二忠、李金风、李盼杰、白瑞苓、李小分、李跃春、刘景峰、林红珍、李小辈、李瑞与被告甄田玺、博野县丰农家庭农场追索劳动报酬纠纷一案，本院于2019年4月28日立案后，依法适用普通程序，于2019年8月21日公开开庭进行了审理。"
    ],
    "procedure": [
      "二十名原告共同诉讼代表人李盼杰、刘景峰到庭参加诉讼，被告甄田玺、被告博野县丰农家庭农场经本院依法公告送达开庭传票传唤，无正当理由未到庭参加诉讼。",
      "本案现已审理终结。",
      "李小霞、李彦芹、赵小敏、费彩玲、史小彩、张爱平、李小舵、张荣芳、李胜吉、楚书芳、李二忠、李金风、李盼杰、白瑞苓、李小分、李跃春、刘景峰、林红珍、李小辈、李瑞向本院提出诉讼请求:1、判令被告立即给付工资46656元；2、本案的诉讼费用由被告担负。",
      "事实与理由:2017年被告雇佣上述原告干农活，共欠到上述原告工资款46656元未给付，并分别出具欠条。",
      "经原告多次索要未果，为维护原告的合法权益，特提起诉讼，要求被告立即给付所欠工资款46656元，望贵院判如所求。",
      "甄田玺未提交答辩意见。",
      "博野县丰农家庭农场未提交答辩意见。"
    ],
    "facts": [
      "经审理查明，2017年二十名原告在被告博野县丰农家庭农场干农活，被告欠工资款未给付。",
      "其中被告经营者甄田玺分别给李盼杰、费彩玲、李小霞、李跃春、史小彩、张荣芳、白瑞芩、李瑞、李胜吉、楚书芳、李二忠、张爱平、李彦芹出具欠据，载明“田玺欠盼杰人民币染仟零肆拾元整（7040元），2017.4.16日。",
      "今收现金伍佰元整，李卫岩，2017.4.25日”、“田玺欠彩玲人民币陆佰陆拾元（660元）,2017.4.15”、“田玺欠小匣人民币陆佰捌拾元（680元），2017.4.15”、“田玺欠跃春人民币贰仟壹佰叁拾元（2130元），2017.4.15”、“田玺欠小彩人民币肆仟零玖拾捌（4098元），2017.4.15”、“田玺欠容芳人民币玖佰玖拾元（990元），2017.4.15”、“田玺欠瑞玲人民币叁仟陆佰柒拾肆元（3674元），2017.4.15”、“田玺欠瑞芬人民币壹仟元整（1000元），2017.4.15”、“田玺欠胜几人民币叁仟贰佰陆拾染（3267元），2017.4.15”、“田玺欠树芳人民币叁仟零伍拾伍（3055元），2017.4.15”、“田玺欠二忠人民币壹仟叁佰壹拾元（1310元），2017.4.15”、“田玺欠爱平人民币壹仟元整（1000元），2017.4.15”、“田玺欠艳芹人民币贰仟贰佰陆拾染（2267元），2017.4.15”。",
      "2017年4月15日被告原人员赵某、李红彬、李某1、李素杰、李某2五人为原告刘景峰、赵小敏、李小辈、林红珍出具了拖欠工资的书面证明，证明被告博野县丰农家庭农场欠刘景峰工钱3000元；欠赵小敏工钱4500元；欠李小辈工钱1900元；欠林红珍工钱985元。",
      "赵某、李某2、李素杰、李某1四人为原告李金风、李小分出具了拖欠工资的书面证明，证明被告博野县丰农家庭农场欠李金风工钱2775元；欠李小分工钱785元。",
      "赵某、李某1、李某2三人为原告李小舵出具了拖欠工资的书面证明，证明被告博野县丰农家庭农场欠李小舵工钱830元。",
      "证人未出庭作证，但庭审后本院核实证人李某2、李某1、赵某，三证人均陈述原为博野县丰农家庭农场人员，证实该农场欠原告上述工资。",
      "在庭审中，原告均认可被告已按所欠数额30%给了原告化肥，起诉数额都要减去30%，就是实际欠的钱。",
      "博野县丰农家庭农场为个体工商户，经营者为甄田玺。"
    ],
    "opinion": [
      "本院认为，原告李盼杰、费彩玲、李小霞、李跃春、史小彩、张荣芳、白瑞苓、李瑞、李胜吉、楚书芳、李二忠、张爱平、李彦芹、李金风、李小分、林红珍、刘景峰、李小舵、赵小敏、李小辈主张被告博野县丰农家庭农场欠工资，有经营者甄田玺出具的欠据及被告博野县丰农家庭农场原人员作证证实，应予认定。",
      "又因原告均认可出具欠条、证明后领取了欠款数额30%的化肥，均同意按照30%扣减确定欠款数额，因此按照原告上述顺序被告工资数额分别为4578元、462元、476元、1491元、2868.6元、693元、2571.8元、700元、2286.9元、2138.5元、917元、700元、1586.9元、1942.5元、549.5元、689.5元、2100元、581元、3150元、1330元。",
      "被告博野县丰农家庭农场性质为个体工商户，原告请求经营者共同承担债务，符合法律规定，应予支持。",
      "综上所述，二十位原告诉讼请求，应按上述确定的拖欠工资数额予以认定支持。"
    ],
    "verdict": [
      "依照《中华人民共和国民法通则》第二十九条  、第八十四条  的规定，判决如下:",
      "被告博野县丰农家庭农场、甄田玺判决生效后三日内给付原告李盼杰工资4578元；给付原告费彩玲工资462元；给付原告李小霞工资476元；给付原告李跃春工资1491元；给付原告史小彩工资2868.6元；给付原告张荣芳工资693元；给付原告白瑞芩工资2571.8元；给付原告李瑞工资700元；给付原告李胜吉工资2286.9元；给付原告楚书芳工资2138.5元；给付原告李二忠工资917元；给付原告张爱平工资700元；给付原告李彦芹工资1586.9元；给付原告李金风工资1942.5元；给付原告李小分工资549.5元；给付原告林红珍工资689.5元；给付原告刘景峰工资2100元；给付原告李小舵工资581元；给付原告赵小敏工资3150元；给付原告李小辈工资1330元；",
      "案件受理费10元，由被告甄田玺、博野县丰农家庭农场共同负担。"
    ],
    "inform": [
      "如不服本判决，可以在判决书送达之日起十五日内，向本院递交上诉状，并按对方当事人或者代表人的人数提出副本，上诉于河北省保定市中级人民法院。"
    ],
    "ending": [
      "审判长赵建辉",
      "审判员江素平",
      "人民陪审员张玉",
      "二〇一九年八月二十七日",
      "书记员王伟"
    ]
  },
  "metadata": {
    "日期": "2019-08-27",
    "法院": "河北省博野县人民法院",
    "案号": "（2019）冀0637民初652号",
    "时间": "2019年08月27日",
    "案由": "追索劳动报酬纠纷",
    "类型": "判决书",
    "程序": "一审"
  }
}