{
  "title": "刘根太与广州市世港服装有限公司劳务合同纠纷一审民事判决书",
  "content": {
    "litigants": [
      "原告:刘根太，男，1953年12月4日出生，汉族，住河南省内黄县。",
      "被告:广州市世港服装有限公司，住所地广东省广州市增城区新塘镇久裕村马牯岭，统一社会信用代码:914401835937270288。",
      "法定代表人:梁翠贞。"
    ],
    "explain": [
      "原告刘根太诉被告广州市世港服装有限公司劳务合同纠纷一案，本院于2018年7月17日立案受理。"
    ],
    "procedure": [
      "原告的诉讼请求为:被告向原告支付劳动报酬5145.1元。",
      "本院依法适用小额诉讼程序，于2018年10月9日公开开庭进行了审理，现已审理终结。"
    ],
    "facts": [
      "本院经审理认定:原告于2017年3月到被告处工作，被告于2018年6月1日关闭了工厂，被告欠下原告两个月的劳动报酬6324元未付，原告向增城区新塘镇劳动所投诉。",
      "后经劳动所调解处理，被告只支付原告66.4%的劳动报酬，仍欠下原告2124.9元劳动报酬未付。",
      "事后，原告向增城区劳动争议仲裁委员会申请仲裁（以下简称仲裁委），仲裁委以原告已超60岁为由不予受理，于是，原告向法院起诉。",
      "被告经本院合法传唤无正当理由拒不到庭应诉及举证。",
      "庭审中，原告诉称其因向被告追讨劳动报酬花一个月时间，故要求被告赔偿一个月劳动报酬3000元，现不要求被告赔偿一个月劳动报酬，只要求被告付清余下劳动报酬2124.9元。",
      "被告欠下原告劳动报酬2124.9元，有原、被告双方签名确认的《工资汇总表》为据，本院予以确认。",
      "现原告要求被告支付清劳动报酬2124.9元，合理合法，本院予以支持。",
      "本院依照《中华人民共和国民法通则》第一百零六条  第一款  、第一百三十四条  第一款  第（四）项  、《最高人民法院关于适用的解释》第九十条、《中华人民共和国民事诉讼法》第一百四十四条  之规定，判决如下:",
      "一、被告广州市世港服装有限公司应于本判决生效之日起五日内向原告刘根太支付劳动报酬2124.9元。",
      "二、驳回原告刘根太的其他诉讼请求。",
      "如未按本判决指定的期间履行给付金钱义务，应当依照《中华人民共和国民事诉讼法》第二百五十三条  之规定，加倍支付迟延履行期间的债务利息。",
      "案件受理费25（原告刘根太已预交），由被告广州市世港服装有限公司负担。",
      "原告刘根太预交的受理费由法院退回。",
      "本判决为终审判决。"
    ],
    "ending": [
      "审判员潘秀麟",
      "二〇一八年十月九日",
      "书记员陈敏仪",
      "本判决所引用的法律条文:",
      "《中华人民共和国民法通则》",
      "第一百零六条公民、法人违反合同或者不履行其他义务的，应当承担民事责任。",
      "公民、法人由于过错侵害国家的、集体的财产，侵害他人财产、人身的应当承担民事责任。",
      "没有过错，但法律规定应当承担民事责任的，应当承担民事责任。",
      "第一百三十四条【承担民事责任的方式】承担民事责任的方式主要有:(一)停止侵害；(二)排除妨碍；(三)消除危险；(四)返还财产；(五)恢复原状；(六)修理、重作、更换；(七)赔偿损失；(八)支付违约金；(九)消除影响、恢复名誉；(十)赔礼道歉。",
      "以上承担民事责任的方式，可以单独适用，也可以合并适用。",
      "人民法院审理民事案件，除适用上述规定外，还可以予以训诫、责令具结悔过、收缴进行非法活动的财物和非法所得，并可以依照法律规定处以罚款、拘留。",
      "《最高人民法院关于适用的解释》",
      "第九十条:当事人对自己提出的诉讼请求所依据的事实或者反驳对方诉讼请求所依据的事实，应当提供证据加以证明，但法律另有规定的除外。",
      "在作出判决前，当事人未能提供证据或者证据不足以证明其事实主张的，由负有举证证明责任的当事人承担不利的后果。",
      "《中华人民共和国民事诉讼法》",
      "第一百四十四条被告经传票传唤，无正当理由拒不到庭的，或者未经法庭许可中途退庭的，可以缺席判决。"
    ]
  },
  "metadata": {
    "日期": "2018-10-09",
    "法院": "广州市增城区人民法院",
    "案号": "（2018）粤118民初4872号",
    "时间": "2018年10月09日",
    "案由": "劳务合同纠纷",
    "类型": "判决书",
    "程序": "一审"
  }
}